beat_tracking_evaluation/__init__.py
beat_tracking_evaluation/evaluation.py
beat_tracking_evaluation-1.1.0.dist-info/licenses/LICENSE.txt
beat_tracking_evaluation-1.1.0.dist-info/METADATA
beat_tracking_evaluation-1.1.0.dist-info/WHEEL
beat_tracking_evaluation-1.1.0.dist-info/top_level.txt
beat_tracking_evaluation-1.1.0.dist-info/RECORD
