Metadata-Version: 2.4
Name: beat-tracking-evaluation
Version: 1.1.0
Summary: Beat tracking evaluation measures
Author: Adam Stark, Matthew Davies
License: MIT
Project-URL: Homepage, https://github.com/adamstark/Beat-Tracking-Evaluation-Toolbox
Project-URL: Repository, https://github.com/adamstark/Beat-Tracking-Evaluation-Toolbox
Keywords: beat tracking,music information retrieval,evaluation,mir
Requires-Python: >=3.8
License-File: LICENSE.txt
Requires-Dist: numpy>=1.20.0
Dynamic: license-file
